LICENSE
README.md
setup.py
sen2nbar/__init__.py
sen2nbar/axioms.py
sen2nbar/brdf.py
sen2nbar/c_factor.py
sen2nbar/kernels.py
sen2nbar/metadata.py
sen2nbar/nbar.py
sen2nbar/utils.py
sen2nbar.egg-info/PKG-INFO
sen2nbar.egg-info/SOURCES.txt
sen2nbar.egg-info/dependency_links.txt
sen2nbar.egg-info/requires.txt
sen2nbar.egg-info/top_level.txt