Metadata-Version: 2.1
Name: sen2nbar
Version: 2023.7.0
Summary: Nadir BRDF Adjusted Reflectance (NBAR) for Sentinel-2 in Python
Home-page: https://github.com/ESDS-Leipzig/sen2nbar
Author: David Montero Loaiza
Author-email: dml.mont@gmail.com
License: MIT
Classifier: Development Status :: 2 - Pre-Alpha
Classifier: License :: OSI Approved :: MIT License
Classifier: Programming Language :: Python
Classifier: Programming Language :: Python :: 3.9
License-File: LICENSE
